sniff/__init__.py
sniff/sniff.py
sniff_admanvoids-0.1.4.dist-info/LICENSE
sniff_admanvoids-0.1.4.dist-info/METADATA
sniff_admanvoids-0.1.4.dist-info/WHEEL
sniff_admanvoids-0.1.4.dist-info/entry_points.txt
sniff_admanvoids-0.1.4.dist-info/top_level.txt
sniff_admanvoids-0.1.4.dist-info/RECORD
