Metadata-Version: 2.1
Name: sniff_admanvoids
Version: 0.1.4
Summary: A package for sniffing website information
Home-page: https://github.com/daveymason/sniff
Author: Davey Mason
Author-email: Davey Mason <daveymason@outlook.com>
Project-URL: Homepage, https://github.com/daveymason/sniff
Project-URL: Issues, https://github.com/daveymason/sniff/issues
Classifier: Programming Language :: Python :: 3
Classifier: License :: OSI Approved :: MIT License
Classifier: Operating System :: OS Independent
Requires-Python: >=3.6
License-File: LICENSE
Requires-Dist: requests
Requires-Dist: beautifulsoup4
Requires-Dist: click
Requires-Dist: python-whois
Requires-Dist: cryptography
